Workbook

Sheet Dashboard
A1: AGREGADOR DE DADOS - IMPOSTO DE RENDA
A3: Ano Base: 2026
A4: Última Atualização: 05/02/2026
A6: NAVEGAÇÃO RÁPIDA
A7: Aba | B7: Descrição
A8: Rendimentos | B8: Salários, pró-labore e outros rendimentos tributáveis
A9: Rendimentos Isentos | B9: Dividendos, PLR e rendimentos não tributáveis
A10: Despesas Dedutíveis | B10: Saúde, educação, previdência e dependentes
A11: Bens e Direitos | B11: Imóveis, veículos, investimentos e outros bens
A12: Dívidas | B12: Financiamentos, empréstimos e outras dívidas
A13: Resumo | B13: Consolidação de todos os dados informados
A15: INDICADORES PRINCIPAIS
A17: Total de Rendimentos Tributáveis: | B17: =Rendimentos!B100 -> 0
A18: Total de Rendimentos Isentos: | B18: ='Rendimentos Isentos'!B50 -> 0
A19: Total de Despesas Dedutíveis: | B19: ='Despesas Dedutíveis'!B100 -> 0
A20: Total de Bens e Direitos: | B20: ='Bens e Direitos'!C100 -> 0

Sheet Rendimentos
A1: RENDIMENTOS TRIBUTÁVEIS
A3: Mês | B3: Fonte Pagadora | C3: CNPJ | D3: Tipo de Rendimento | E3: Valor Bruto | F3: IRRF
A4: Janeiro
A5: Fevereiro
A6: Março
A7: Abril
A8: Maio
A9: Junho
A10: Julho
A11: Agosto
A12: Setembro
A13: Outubro
A14: Novembro
A15: Dezembro
A100: TOTAL ANUAL | B100: =SUM(E4:E15) -> 0 | E100: =SUM(E4:E15) -> 0 | F100: =SUM(F4:F15) -> 0

Sheet Rendimentos Isentos
A1: RENDIMENTOS ISENTOS E NÃO TRIBUTÁVEIS
A3: Tipo | B3: Fonte Pagadora | C3: CNPJ | D3: Valor
A4: Dividendos
A5: PLR
A6: Indenizações
A7: Rendimento Poupança
A8: Lucro na Venda de Imóvel Residencial
A9: Outros
A50: TOTAL | B50: =SUM(D4:D10) -> 0 | D50: =SUM(D4:D10) -> 0

Sheet Despesas Dedutíveis
A1: DESPESAS DEDUTÍVEIS
A3: Categoria | B3: Beneficiário | C3: CPF/CNPJ | D3: Descrição | E3: Valor
A5: SAÚDE
A6: Plano de Saúde
A7: Consultas Médicas
A8: Exames
A9: Odontologia
A10: Fisioterapia
A11: Outros - Saúde
A12: Subtotal Saúde | E12: =SUM(E6:E11) -> 0
A14: EDUCAÇÃO
A15: Ensino Fundamental
A16: Ensino Médio
A17: Ensino Superior
A18: Pós-Graduação
A19: Ensino Técnico
A20: Subtotal Educação | E20: =SUM(E15:E19) -> 0
A22: PREVIDÊNCIA PRIVADA
A23: PGBL
A25: DEPENDENTES
A30: Subtotal Dependentes | E30: =SUM(E26:E29) -> 0
A100: TOTAL GERAL DEDUTÍVEL | B100: =E12+E20+E23+E30 -> 0 | E100: =E12+E20+E23+E30 -> 0

Sheet Bens e Direitos
A1: BENS E DIREITOS
A3: Código | B3: Discriminação | C3: Localização | D3: Valor 31/12/2024 | E3: Valor 31/12/2025 | F3: Observações
A4: 11 | B4: Apartamento
A5: 12 | B5: Casa
A6: 13 | B6: Terreno
A7: 14 | B7: Sala ou Conjunto
A8: 21 | B8: Veículo Automotor Terrestre
A9: 31 | B9: Conta Corrente
A10: 45 | B10: Aplicação de Renda Fixa
A11: 47 | B11: Fundo de Investimento
A12: 99 | B12: Outros Bens e Direitos
A100: TOTAL | C100: =E4+E5+E6+E7+E8+E9+E10+E11+E12 -> 0 | D100: =SUM(D4:D20) -> 0 | E100: =SUM(E4:E20) -> 0

Sheet Dívidas
A1: DÍVIDAS E ÔNUS REAIS
A3: Código | B3: Discriminação | C3: Credor | D3: Valor 31/12/2024 | E3: Valor 31/12/2025 | F3: Observações
A4: 11 | B4: Financiamento Imobiliário
A5: 12 | B5: Financiamento de Veículos
A6: 13 | B6: Empréstimo Bancário
A7: 14 | B7: Cartão de Crédito
A8: 99 | B8: Outras Dívidas
A50: TOTAL | D50: =SUM(D4:D10) -> 0 | E50: =SUM(E4:E10) -> 0

Sheet Resumo
A1: RESUMO CONSOLIDADO - DECLARAÇÃO DE IMPOSTO DE RENDA
A3: Ano-Base: 2026
A5: RENDIMENTOS
A6: Rendimentos Tributáveis | B6: =Rendimentos!B100 -> 0
A7: (-) IRRF Retido | B7: =Rendimentos!F100 -> 0
A8: Rendimentos Isentos | B8: ='Rendimentos Isentos'!B50 -> 0
A10: DEDUÇÕES
A11: Total de Despesas Dedutíveis | B11: ='Despesas Dedutíveis'!B100 -> 0
A13: PATRIMÔNIO
A14: Total de Bens e Direitos (2025) | B14: ='Bens e Direitos'!E100 -> 0
A15: Total de Dívidas (2025) | B15: =Dívidas!E50 -> 0
A16: Patrimônio Líquido | B16: =B14-B15 -> 0
A19: OBSERVAÇÕES IMPORTANTES
A20: 1. Esta planilha é uma ferramenta auxiliar de organização
A21: 2. Sempre confira os dados com documentos oficiais
A22: 3. Consulte um contador para orientações específicas
A23: 4. Mantenha os comprovantes guardados por 5 anos
